{
    "$schema": "https://schemas.premid.app/metadata/1.7",
    "author": {
      "name": "usernamee#8983",
      "id": "446755254160064512"
    },
    "contributors": [
      {
        "name": "JacobG27#4533",
        "id": "224060739684401153"
      }
    ],
    "service": "DankVM",
    "altnames": ["Dank VM", "dank-vm"],
    "description": {
      "en": "Control virtual machines with strangers."
    },
    "url": "dank-vm.xyz",
    "version": "1.0",
    "logo": "https://cdn.discordapp.com/icons/963138693139423292/1ae7835533de2a759591fb45cc4eb11f.png?size=512",
    "thumbnail": "https://cdn.discordapp.com/icons/963138693139423292/1ae7835533de2a759591fb45cc4eb11f.png?size=128",
    "color": "#ffffff",
    "tags": ["vm", "dankvm","qemu","windows"],
    "category": "other",
    "regExp": "http:\\/\\/dank-vm\\.xyz\\/dank-vm.*",
    "iframe": false,
    "readLogs": false,
    "settings": [
      {
        "id": "ID",
        "multiLanguage": false
      }
    ]
  }